importscanner/__init__.py
importscanner/cli.py
py_import_scanner-0.1.1.dist-info/licenses/LICENSE
py_import_scanner-0.1.1.dist-info/METADATA
py_import_scanner-0.1.1.dist-info/WHEEL
py_import_scanner-0.1.1.dist-info/entry_points.txt
py_import_scanner-0.1.1.dist-info/top_level.txt
py_import_scanner-0.1.1.dist-info/RECORD
